odoo9_addon_account_payment_return_import_sepa_pain-9.0.1.0.0-py2.7-nspkg.pth
odoo9_addon_account_payment_return_import_sepa_pain-9.0.1.0.0.dist-info/DESCRIPTION.rst
odoo9_addon_account_payment_return_import_sepa_pain-9.0.1.0.0.dist-info/METADATA
odoo9_addon_account_payment_return_import_sepa_pain-9.0.1.0.0.dist-info/RECORD
odoo9_addon_account_payment_return_import_sepa_pain-9.0.1.0.0.dist-info/WHEEL
odoo9_addon_account_payment_return_import_sepa_pain-9.0.1.0.0.dist-info/metadata.json
odoo9_addon_account_payment_return_import_sepa_pain-9.0.1.0.0.dist-info/namespace_packages.txt
odoo9_addon_account_payment_return_import_sepa_pain-9.0.1.0.0.dist-info/top_level.txt
odoo_addons/account_payment_return_import_sepa_pain/README.rst
odoo_addons/account_payment_return_import_sepa_pain/__init__.py
odoo_addons/account_payment_return_import_sepa_pain/__openerp__.py
odoo_addons/account_payment_return_import_sepa_pain/data/unpaid_reason_codes.xml
odoo_addons/account_payment_return_import_sepa_pain/i18n/de.po
odoo_addons/account_payment_return_import_sepa_pain/i18n/es.po
odoo_addons/account_payment_return_import_sepa_pain/i18n/sl.po
odoo_addons/account_payment_return_import_sepa_pain/models/__init__.py
odoo_addons/account_payment_return_import_sepa_pain/models/payment_return.py
odoo_addons/account_payment_return_import_sepa_pain/static/description/icon.png
odoo_addons/account_payment_return_import_sepa_pain/static/description/icon.svg
odoo_addons/account_payment_return_import_sepa_pain/test_files/test-sepa-unpaid.xml
odoo_addons/account_payment_return_import_sepa_pain/test_files/test-sepa-unpaid.zip
odoo_addons/account_payment_return_import_sepa_pain/tests/__init__.py
odoo_addons/account_payment_return_import_sepa_pain/tests/test_import_sepa_pain.py
odoo_addons/account_payment_return_import_sepa_pain/wizard/__init__.py
odoo_addons/account_payment_return_import_sepa_pain/wizard/pain_parser.py
odoo_addons/account_payment_return_import_sepa_pain/wizard/payment_return_import.py
